<?xml version="1.0" encoding="UTF-8"?>
<con:soapui-project id="290649e3-6350-436f-a7b4-b5d6204e9534" activeEnvironment="Default" name="SOAPUI project for SOAP Service-Assignment_calc" resourceRoot="" soapui-version="5.7.0" abortOnError="false" runType="SEQUENTIAL" xmlns:con="http://eviware.com/soapui/config"><con:settings/><con:interface xsi:type="con:WsdlInterface" id="24856d04-fa23-4d74-8c72-6e80e36f0544" wsaVersion="NONE" name="CalculatorSoap12" type="wsdl" bindingName="{http://tempuri.org/}CalculatorSoap12" soapVersion="1_2" anonymous="optional" definition="http://www.dneonline.com/calculator.asmx?wsdl" xmlns:xsi="http://www.w3.org/2001/XMLSchema-instance"><con:settings/><con:definitionCache/><con:endpoints><con:endpoint>http://www.dneonline.com/calculator.asmx</con:endpoint></con:endpoints><con:operation id="aa7cd6c8-b882-48b2-8bfe-cdb8626a5279" isOneWay="false" action="http://tempuri.org/Add" name="Add" bindingOperationName="Add" type="Request-Response" inputName="" receivesAttachments="false" sendsAttachments="false" anonymous="optional"><con:settings/><con:call id="f10a7615-77f5-4224-954a-207346ff36cf" name="Request 1"><con:settings><con:setting id="com.eviware.soapui.impl.wsdl.WsdlRequest@request-headers">&lt;xml-fragment/></con:setting></con:settings><con:encoding>UTF-8</con:encoding><con:endpoint>http://www.dneonline.com/calculator.asmx</con:endpoint><con:request><![CDATA[<soap:Envelope xmlns:soap="http://www.w3.org/2003/05/soap-envelope" xmlns:tem="http://tempuri.org/">\r
   <soap:Header/>\r
   <soap:Body>\r
      <tem:Add>\r
         <tem:intA>1</tem:intA>\r
         <tem:intB>2</tem:intB>\r
      </tem:Add>\r
   </soap:Body>\r
</soap:Envelope>]]></con:request><con:credentials><con:authType>No Authorization</con:authType></con:credentials><con:jmsConfig JMSDeliveryMode="PERSISTENT"/><con:jmsPropertyConfig/><con:wsaConfig mustUnderstand="NONE" version="200508" action="http://tempuri.org/CalculatorSoap/AddRequest"/><con:wsrmConfig version="1.2"/></con:call></con:operation><con:operation id="20e19424-77aa-4344-b03d-2c4fc41c981d" isOneWay="false" action="http://tempuri.org/Divide" name="Divide" bindingOperationName="Divide" type="Request-Response" inputName="" receivesAttachments="false" sendsAttachments="false" anonymous="optional"><con:settings/><con:call id="8032efb9-d455-427c-bfeb-57d9c198069a" name="Request 1"><con:settings/><con:encoding>UTF-8</con:encoding><con:endpoint>http://www.dneonline.com/calculator.asmx</con:endpoint><con:request><![CDATA[<soap:Envelope xmlns:soap="http://www.w3.org/2003/05/soap-envelope" xmlns:tem="http://tempuri.org/">\r
   <soap:Header/>\r
   <soap:Body>\r
      <tem:Divide>\r
         <tem:intA>?</tem:intA>\r
         <tem:intB>?</tem:intB>\r
      </tem:Divide>\r
   </soap:Body>\r
</soap:Envelope>]]></con:request><con:wsaConfig mustUnderstand="NONE" version="200508" action="http://tempuri.org/CalculatorSoap/DivideRequest"/></con:call></con:operation><con:operation id="5e8ac497-8c67-439b-a6b5-7d3dc9564367" isOneWay="false" action="http://tempuri.org/Multiply" name="Multiply" bindingOperationName="Multiply" type="Request-Response" inputName="" receivesAttachments="false" sendsAttachments="false" anonymous="optional"><con:settings/><con:call id="66113238-b285-46d6-a32f-0afc053729ac" name="Request 1"><con:settings/><con:encoding>UTF-8</con:encoding><con:endpoint>http://www.dneonline.com/calculator.asmx</con:endpoint><con:request><![CDATA[<soap:Envelope xmlns:soap="http://www.w3.org/2003/05/soap-envelope" xmlns:tem="http://tempuri.org/">\r
   <soap:Header/>\r
   <soap:Body>\r
      <tem:Multiply>\r
         <tem:intA>?</tem:intA>\r
         <tem:intB>?</tem:intB>\r
      </tem:Multiply>\r
   </soap:Body>\r
</soap:Envelope>]]></con:request><con:wsaConfig mustUnderstand="NONE" version="200508" action="http://tempuri.org/CalculatorSoap/MultiplyRequest"/></con:call></con:operation><con:operation id="aebce205-a0e3-4bd0-a65b-be167acde3b1" isOneWay="false" action="http://tempuri.org/Subtract" name="Subtract" bindingOperationName="Subtract" type="Request-Response" inputName="" receivesAttachments="false" sendsAttachments="false" anonymous="optional"><con:settings/><con:call id="ec47b24c-bd2d-4b66-8f9f-05825022dcb0" name="Request 1"><con:settings/><con:encoding>UTF-8</con:encoding><con:endpoint>http://www.dneonline.com/calculator.asmx</con:endpoint><con:request><![CDATA[<soap:Envelope xmlns:soap="http://www.w3.org/2003/05/soap-envelope" xmlns:tem="http://tempuri.org/">\r
   <soap:Header/>\r
   <soap:Body>\r
      <tem:Subtract>\r
         <tem:intA>?</tem:intA>\r
         <tem:intB>?</tem:intB>\r
      </tem:Subtract>\r
   </soap:Body>\r
</soap:Envelope>]]></con:request><con:wsaConfig mustUnderstand="NONE" version="200508" action="http://tempuri.org/CalculatorSoap/SubtractRequest"/></con:call></con:operation></con:interface><con:interface xsi:type="con:WsdlInterface" id="323c1df3-a0e4-45f5-aaa5-997b649cd8af" wsaVersion="NONE" name="CalculatorSoap" type="wsdl" bindingName="{http://tempuri.org/}CalculatorSoap" soapVersion="1_1" anonymous="optional" definition="http://www.dneonline.com/calculator.asmx?wsdl" xmlns:xsi="http://www.w3.org/2001/XMLSchema-instance"><con:settings/><con:definitionCache type="TEXT" rootPart="http://www.dneonline.com/calculator.asmx?wsdl"><con:part><con:url>http://www.dneonline.com/calculator.asmx?wsdl</con:url><con:content><![CDATA[<wsdl:definitions targetNamespace="http://tempuri.org/" xmlns:soap="http://schemas.xmlsoap.org/wsdl/soap/" xmlns:tm="http://microsoft.com/wsdl/mime/textMatching/" xmlns:soapenc="http://schemas.xmlsoap.org/soap/encoding/" xmlns:mime="http://schemas.xmlsoap.org/wsdl/mime/" xmlns:tns="http://tempuri.org/" xmlns:s="http://www.w3.org/2001/XMLSchema" xmlns:soap12="http://schemas.xmlsoap.org/wsdl/soap12/" xmlns:http="http://schemas.xmlsoap.org/wsdl/http/" xmlns:wsdl="http://schemas.xmlsoap.org/wsdl/">
  <wsdl:types>
    <s:schema elementFormDefault="qualified" targetNamespace="http://tempuri.org/">
      <s:element name="Add">
        <s:complexType>
          <s:sequence>
            <s:element minOccurs="1" maxOccurs="1" name="intA" type="s:int"/>
            <s:element minOccurs="1" maxOccurs="1" name="intB" type="s:int"/>
          </s:sequence>
        </s:complexType>
      </s:element>
      <s:element name="AddResponse">
        <s:complexType>
          <s:sequence>
            <s:element minOccurs="1" maxOccurs="1" name="AddResult" type="s:int"/>
          </s:sequence>
        </s:complexType>
      </s:element>
      <s:element name="Subtract">
        <s:complexType>
          <s:sequence>
            <s:element minOccurs="1" maxOccurs="1" name="intA" type="s:int"/>
            <s:element minOccurs="1" maxOccurs="1" name="intB" type="s:int"/>
          </s:sequence>
        </s:complexType>
      </s:element>
      <s:element name="SubtractResponse">
        <s:complexType>
          <s:sequence>
            <s:element minOccurs="1" maxOccurs="1" name="SubtractResult" type="s:int"/>
          </s:sequence>
        </s:complexType>
      </s:element>
      <s:element name="Multiply">
        <s:complexType>
          <s:sequence>
            <s:element minOccurs="1" maxOccurs="1" name="intA" type="s:int"/>
            <s:element minOccurs="1" maxOccurs="1" name="intB" type="s:int"/>
          </s:sequence>
        </s:complexType>
      </s:element>
      <s:element name="MultiplyResponse">
        <s:complexType>
          <s:sequence>
            <s:element minOccurs="1" maxOccurs="1" name="MultiplyResult" type="s:int"/>
          </s:sequence>
        </s:complexType>
      </s:element>
      <s:element name="Divide">
        <s:complexType>
          <s:sequence>
            <s:element minOccurs="1" maxOccurs="1" name="intA" type="s:int"/>
            <s:element minOccurs="1" maxOccurs="1" name="intB" type="s:int"/>
          </s:sequence>
        </s:complexType>
      </s:element>
      <s:element name="DivideResponse">
        <s:complexType>
          <s:sequence>
            <s:element minOccurs="1" maxOccurs="1" name="DivideResult" type="s:int"/>
          </s:sequence>
        </s:complexType>
      </s:element>
    </s:schema>
  </wsdl:types>
  <wsdl:message name="AddSoapIn">
    <wsdl:part name="parameters" element="tns:Add"/>
  </wsdl:message>
  <wsdl:message name="AddSoapOut">
    <wsdl:part name="parameters" element="tns:AddResponse"/>
  </wsdl:message>
  <wsdl:message name="SubtractSoapIn">
    <wsdl:part name="parameters" element="tns:Subtract"/>
  </wsdl:message>
  <wsdl:message name="SubtractSoapOut">
    <wsdl:part name="parameters" element="tns:SubtractResponse"/>
  </wsdl:message>
  <wsdl:message name="MultiplySoapIn">
    <wsdl:part name="parameters" element="tns:Multiply"/>
  </wsdl:message>
  <wsdl:message name="MultiplySoapOut">
    <wsdl:part name="parameters" element="tns:MultiplyResponse"/>
  </wsdl:message>
  <wsdl:message name="DivideSoapIn">
    <wsdl:part name="parameters" element="tns:Divide"/>
  </wsdl:message>
  <wsdl:message name="DivideSoapOut">
    <wsdl:part name="parameters" element="tns:DivideResponse"/>
  </wsdl:message>
  <wsdl:portType name="CalculatorSoap">
    <wsdl:operation name="Add">
      <wsdl:documentation>Adds two integers. This is a test WebService. ©DNE Online</wsdl:documentation>
      <wsdl:input message="tns:AddSoapIn"/>
      <wsdl:output message="tns:AddSoapOut"/>
    </wsdl:operation>
    <wsdl:operation name="Subtract">
      <wsdl:input message="tns:SubtractSoapIn"/>
      <wsdl:output message="tns:SubtractSoapOut"/>
    </wsdl:operation>
    <wsdl:operation name="Multiply">
      <wsdl:input message="tns:MultiplySoapIn"/>
      <wsdl:output message="tns:MultiplySoapOut"/>
    </wsdl:operation>
    <wsdl:operation name="Divide">
      <wsdl:input message="tns:DivideSoapIn"/>
      <wsdl:output message="tns:DivideSoapOut"/>
    </wsdl:operation>
  </wsdl:portType>
  <wsdl:binding name="CalculatorSoap" type="tns:CalculatorSoap">
    <soap:binding transport="http://schemas.xmlsoap.org/soap/http"/>
    <wsdl:operation name="Add">
      <soap:operation soapAction="http://tempuri.org/Add" style="document"/>
      <wsdl:input>
        <soap:body use="literal"/>
      </wsdl:input>
      <wsdl:output>
        <soap:body use="literal"/>
      </wsdl:output>
    </wsdl:operation>
    <wsdl:operation name="Subtract">
      <soap:operation soapAction="http://tempuri.org/Subtract" style="document"/>
      <wsdl:input>
        <soap:body use="literal"/>
      </wsdl:input>
      <wsdl:output>
        <soap:body use="literal"/>
      </wsdl:output>
    </wsdl:operation>
    <wsdl:operation name="Multiply">
      <soap:operation soapAction="http://tempuri.org/Multiply" style="document"/>
      <wsdl:input>
        <soap:body use="literal"/>
      </wsdl:input>
      <wsdl:output>
        <soap:body use="literal"/>
      </wsdl:output>
    </wsdl:operation>
    <wsdl:operation name="Divide">
      <soap:operation soapAction="http://tempuri.org/Divide" style="document"/>
      <wsdl:input>
        <soap:body use="literal"/>
      </wsdl:input>
      <wsdl:output>
        <soap:body use="literal"/>
      </wsdl:output>
    </wsdl:operation>
  </wsdl:binding>
  <wsdl:binding name="CalculatorSoap12" type="tns:CalculatorSoap">
    <soap12:binding transport="http://schemas.xmlsoap.org/soap/http"/>
    <wsdl:operation name="Add">
      <soap12:operation soapAction="http://tempuri.org/Add" style="document"/>
      <wsdl:input>
        <soap12:body use="literal"/>
      </wsdl:input>
      <wsdl:output>
        <soap12:body use="literal"/>
      </wsdl:output>
    </wsdl:operation>
    <wsdl:operation name="Subtract">
      <soap12:operation soapAction="http://tempuri.org/Subtract" style="document"/>
      <wsdl:input>
        <soap12:body use="literal"/>
      </wsdl:input>
      <wsdl:output>
        <soap12:body use="literal"/>
      </wsdl:output>
    </wsdl:operation>
    <wsdl:operation name="Multiply">
      <soap12:operation soapAction="http://tempuri.org/Multiply" style="document"/>
      <wsdl:input>
        <soap12:body use="literal"/>
      </wsdl:input>
      <wsdl:output>
        <soap12:body use="literal"/>
      </wsdl:output>
    </wsdl:operation>
    <wsdl:operation name="Divide">
      <soap12:operation soapAction="http://tempuri.org/Divide" style="document"/>
      <wsdl:input>
        <soap12:body use="literal"/>
      </wsdl:input>
      <wsdl:output>
        <soap12:body use="literal"/>
      </wsdl:output>
    </wsdl:operation>
  </wsdl:binding>
  <wsdl:service name="Calculator">
    <wsdl:port name="CalculatorSoap" binding="tns:CalculatorSoap">
      <soap:address location="http://www.dneonline.com/calculator.asmx"/>
    </wsdl:port>
    <wsdl:port name="CalculatorSoap12" binding="tns:CalculatorSoap12">
      <soap12:address location="http://www.dneonline.com/calculator.asmx"/>
    </wsdl:port>
  </wsdl:service>
</wsdl:definitions>]]></con:content><con:type>http://schemas.xmlsoap.org/wsdl/</con:type></con:part></con:definitionCache><con:endpoints><con:endpoint>http://IN002YHZ:8088/mockCalculatorSoap</con:endpoint><con:endpoint>http://www.dneonline.com/calculator.asmx</con:endpoint></con:endpoints><con:operation id="32bed7e8-bdbe-4735-8c00-3e49a29b1d5f" isOneWay="false" action="http://tempuri.org/Add" name="Add" bindingOperationName="Add" type="Request-Response" inputName="" receivesAttachments="false" sendsAttachments="false" anonymous="optional"><con:settings/><con:call id="0a72048e-aaea-430d-924d-409d0b019b22" name="Request 1"><con:settings><con:setting id="com.eviware.soapui.impl.wsdl.WsdlRequest@request-headers">&lt;xml-fragment/></con:setting></con:settings><con:encoding>UTF-8</con:encoding><con:endpoint>http://IN002YHZ:8088/mockCalculatorSoap</con:endpoint><con:request><![CDATA[<soapenv:Envelope xmlns:soapenv="http://schemas.xmlsoap.org/soap/envelope/" xmlns:tem="http://tempuri.org/">\r
   <soapenv:Header/>\r
   <soapenv:Body>\r
      <tem:Add>\r
         <tem:intA>1</tem:intA>\r
         <tem:intB>2</tem:intB>\r
      </tem:Add>\r
   </soapenv:Body>\r
</soapenv:Envelope>]]></con:request><con:credentials><con:authType>No Authorization</con:authType></con:credentials><con:jmsConfig JMSDeliveryMode="PERSISTENT"/><con:jmsPropertyConfig/><con:wsaConfig mustUnderstand="NONE" version="200508" action="http://tempuri.org/Add"/><con:wsrmConfig version="1.2"/></con:call></con:operation><con:operation id="e7c82778-f548-477b-bf9f-48e4004e55db" isOneWay="false" action="http://tempuri.org/Divide" name="Divide" bindingOperationName="Divide" type="Request-Response" inputName="" receivesAttachments="false" sendsAttachments="false" anonymous="optional"><con:settings/><con:call id="509f6da5-b73e-4c34-ae95-fee9e1f91dc7" name="Request 1"><con:settings/><con:encoding>UTF-8</con:encoding><con:endpoint>http://www.dneonline.com/calculator.asmx</con:endpoint><con:request><![CDATA[<soapenv:Envelope xmlns:soapenv="http://schemas.xmlsoap.org/soap/envelope/" xmlns:tem="http://tempuri.org/">\r
   <soapenv:Header/>\r
   <soapenv:Body>\r
      <tem:Divide>\r
         <tem:intA>?</tem:intA>\r
         <tem:intB>?</tem:intB>\r
      </tem:Divide>\r
   </soapenv:Body>\r
</soapenv:Envelope>]]></con:request><con:wsaConfig mustUnderstand="NONE" version="200508" action="http://tempuri.org/Divide"/></con:call></con:operation><con:operation id="0731b4f8-a568-4426-b1b5-e7b0a6bc8470" isOneWay="false" action="http://tempuri.org/Multiply" name="Multiply" bindingOperationName="Multiply" type="Request-Response" inputName="" receivesAttachments="false" sendsAttachments="false" anonymous="optional"><con:settings/><con:call id="a46dc3e7-c366-48bc-bc61-64de7051fe5b" name="Request 1"><con:settings><con:setting id="com.eviware.soapui.impl.wsdl.WsdlRequest@request-headers">&lt;xml-fragment/></con:setting></con:settings><con:encoding>UTF-8</con:encoding><con:endpoint>http://www.dneonline.com/calculator.asmx</con:endpoint><con:request><![CDATA[<soapenv:Envelope xmlns:soapenv="http://schemas.xmlsoap.org/soap/envelope/" xmlns:tem="http://tempuri.org/">\r
   <soapenv:Header/>\r
   <soapenv:Body>\r
      <tem:Multiply>\r
         <tem:intA>1</tem:intA>\r
         <tem:intB>4</tem:intB>\r
      </tem:Multiply>\r
   </soapenv:Body>\r
</soapenv:Envelope>]]></con:request><con:credentials><con:authType>No Authorization</con:authType></con:credentials><con:jmsConfig JMSDeliveryMode="PERSISTENT"/><con:jmsPropertyConfig/><con:wsaConfig mustUnderstand="NONE" version="200508" action="http://tempuri.org/Multiply"/><con:wsrmConfig version="1.2"/></con:call></con:operation><con:operation id="f8be1808-c588-48bc-8216-411f489765ee" isOneWay="false" action="http://tempuri.org/Subtract" name="Subtract" bindingOperationName="Subtract" type="Request-Response" inputName="" receivesAttachments="false" sendsAttachments="false" anonymous="optional"><con:settings/><con:call id="27d5bf3f-be8f-4bfd-96c4-8633bdcbaec2" name="Request 1"><con:settings/><con:encoding>UTF-8</con:encoding><con:endpoint>http://www.dneonline.com/calculator.asmx</con:endpoint><con:request><![CDATA[<soapenv:Envelope xmlns:soapenv="http://schemas.xmlsoap.org/soap/envelope/" xmlns:tem="http://tempuri.org/">\r
   <soapenv:Header/>\r
   <soapenv:Body>\r
      <tem:Subtract>\r
         <tem:intA>?</tem:intA>\r
         <tem:intB>?</tem:intB>\r
      </tem:Subtract>\r
   </soapenv:Body>\r
</soapenv:Envelope>]]></con:request><con:wsaConfig mustUnderstand="NONE" version="200508" action="http://tempuri.org/Subtract"/></con:call></con:operation></con:interface><con:testSuite id="e42a79f2-d270-4a45-ab06-1501ca4166bc" name="TestSuite 1"><con:settings/><con:runType>SEQUENTIAL</con:runType><con:testCase id="9262da5b-0d63-4f16-a7d2-11d871e128cf" failOnError="true" failTestCaseOnErrors="true" keepSession="false" maxResults="0" name="TestCase 1" searchProperties="true"><con:settings/><con:testStep type="request" id="c1e12072-1e5c-472b-952a-59ad37532703" name="Add - Request 1"><con:settings/><con:config xsi:type="con:RequestStep" xmlns:xsi="http://www.w3.org/2001/XMLSchema-instance"><con:interface>CalculatorSoap</con:interface><con:operation>Add</con:operation><con:request name="Add - Request 1" outgoingWss="" incomingWss="" timeout="" sslKeystore="" useWsAddressing="false" useWsReliableMessaging="false" wssPasswordType="" id="2d7f9339-749b-4db9-92c1-5fc0a0aa001c"><con:settings><con:setting id="com.eviware.soapui.impl.wsdl.WsdlRequest@request-headers">&lt;xml-fragment/></con:setting></con:settings><con:encoding>UTF-8</con:encoding><con:endpoint>http://IN002YHZ:8088/mockCalculatorSoap</con:endpoint><con:request><![CDATA[<soapenv:Envelope xmlns:soapenv="http://schemas.xmlsoap.org/soap/envelope/" xmlns:tem="http://tempuri.org/">\r
   <soapenv:Header/>\r
   <soapenv:Body>\r
      <tem:Add>\r
         <tem:intA>1</tem:intA>\r
         <tem:intB>2</tem:intB>\r
      </tem:Add>\r
   </soapenv:Body>\r
</soapenv:Envelope>]]></con:request><con:credentials><con:authType>No Authorization</con:authType></con:credentials><con:jmsConfig JMSDeliveryMode="PERSISTENT"/><con:jmsPropertyConfig/><con:wsaConfig mustUnderstand="NONE" version="200508" action="http://tempuri.org/Add"/><con:wsrmConfig version="1.2"/></con:request></con:config></con:testStep><con:properties/></con:testCase><con:properties/></con:testSuite><con:mockService id="2bcbe301-fae2-4441-9092-a793022d2b58" port="8088" path="/mockCalculatorSoap" host="IN002YHZ" name="CalculatorSoap MockService"><con:settings><con:setting id="com.eviware.soapui.impl.wsdl.mock.WsdlMockService@require-soap-action">false</con:setting></con:settings><con:properties/><con:mockOperation name="Add" id="4d973006-ddbb-4d14-b733-ee5bcc87fe30" interface="CalculatorSoap" operation="Add"><con:settings/><con:defaultResponse>Response 1</con:defaultResponse><con:dispatchStyle>SEQUENCE</con:dispatchStyle><con:response name="Response 1" id="8d6158b7-60cd-4454-b8a1-71cf37826fe8" httpResponseStatus="200" encoding="UTF-8"><con:settings/><con:responseContent><![CDATA[<soapenv:Envelope xmlns:soapenv="http://schemas.xmlsoap.org/soap/envelope/" xmlns:tem="http://tempuri.org/">
   <soapenv:Header/>
   <soapenv:Body>
      <tem:AddResponse>
         <tem:AddResult>0</tem:AddResult>
      </tem:AddResponse>
   </soapenv:Body>
</soapenv:Envelope>]]></con:responseContent><con:wsaConfig mustUnderstand="NONE" version="200508" action="http://tempuri.org/Add"/></con:response><con:dispatchConfig/></con:mockOperation><con:mockOperation name="Divide" id="76a094a4-34f5-4a7c-a564-2410adb854ac" interface="CalculatorSoap" operation="Divide"><con:settings/><con:defaultResponse>Response 1</con:defaultResponse><con:dispatchStyle>SEQUENCE</con:dispatchStyle><con:response name="Response 1" id="eff938e3-bea5-4c6c-9511-75dd95bf5eb4" httpResponseStatus="200" encoding="UTF-8"><con:settings/><con:responseContent><![CDATA[<soapenv:Envelope xmlns:soapenv="http://schemas.xmlsoap.org/soap/envelope/" xmlns:tem="http://tempuri.org/">
   <soapenv:Header/>
   <soapenv:Body>
      <tem:DivideResponse>
         <tem:DivideResult>?</tem:DivideResult>
      </tem:DivideResponse>
   </soapenv:Body>
</soapenv:Envelope>]]></con:responseContent><con:wsaConfig mustUnderstand="NONE" version="200508" action="http://tempuri.org/Divide"/></con:response><con:dispatchConfig/></con:mockOperation><con:mockOperation name="Multiply" id="1ff1fb3b-a071-486a-ac4c-4980f8a2d58f" interface="CalculatorSoap" operation="Multiply"><con:settings/><con:defaultResponse>Response 1</con:defaultResponse><con:dispatchStyle>SEQUENCE</con:dispatchStyle><con:response name="Response 1" id="049e9f80-1f3a-4089-ab81-21076e59714f" httpResponseStatus="200" encoding="UTF-8"><con:settings/><con:responseContent><![CDATA[<soapenv:Envelope xmlns:soapenv="http://schemas.xmlsoap.org/soap/envelope/" xmlns:tem="http://tempuri.org/">
   <soapenv:Header/>
   <soapenv:Body>
      <tem:MultiplyResponse>
         <tem:MultiplyResult>?</tem:MultiplyResult>
      </tem:MultiplyResponse>
   </soapenv:Body>
</soapenv:Envelope>]]></con:responseContent><con:wsaConfig mustUnderstand="NONE" version="200508" action="http://tempuri.org/Multiply"/></con:response><con:dispatchConfig/></con:mockOperation><con:mockOperation name="Subtract" id="46a6435d-4e08-4aac-bb2d-03424ea43d01" interface="CalculatorSoap" operation="Subtract"><con:settings/><con:defaultResponse>Response 1</con:defaultResponse><con:dispatchStyle>SEQUENCE</con:dispatchStyle><con:response name="Response 1" id="7081ef56-8a71-4171-8fd5-2d0ca6957414" httpResponseStatus="200" encoding="UTF-8"><con:settings/><con:responseContent><![CDATA[<soapenv:Envelope xmlns:soapenv="http://schemas.xmlsoap.org/soap/envelope/" xmlns:tem="http://tempuri.org/">
   <soapenv:Header/>
   <soapenv:Body>
      <tem:SubtractResponse>
         <tem:SubtractResult>?</tem:SubtractResult>
      </tem:SubtractResponse>
   </soapenv:Body>
</soapenv:Envelope>]]></con:responseContent><con:wsaConfig mustUnderstand="NONE" version="200508" action="http://tempuri.org/Subtract"/></con:response><con:dispatchConfig/></con:mockOperation></con:mockService><con:properties/><con:wssContainer/><con:oAuth2ProfileContainer/><con:oAuth1ProfileContainer/><con:sensitiveInformation/></con:soapui-project>